samlauthenticator/__init__.py
samlauthenticator/samlauthenticator.py
jupyters-0.0.6.dist-info/METADATA
jupyters-0.0.6.dist-info/WHEEL
jupyters-0.0.6.dist-info/top_level.txt
jupyters-0.0.6.dist-info/RECORD
