Metadata-Version: 2.1
Name: jupyters
Version: 0.0.6
Summary: UNKNOWN
Home-page: UNKNOWN
Author: 
Author-email: 
License: UNKNOWN
Platform: UNKNOWN
Classifier: Programming Language :: Python :: 3.6
Classifier: Programming Language :: Python :: 3.7
Classifier: Operating System :: OS Independent
Requires-Dist: Jinja2 (>=2.4)
Requires-Dist: jupyterhub (>=0.9.0)
Requires-Dist: lxml (>=4.2.1)
Requires-Dist: signxml (>=2.6.0)
Requires-Dist: pytz (>=2019.1)
Provides-Extra: tests
Requires-Dist: pytest (>=4.0.0) ; extra == 'tests'
Requires-Dist: pytest-asyncio (>=0.10.0) ; extra == 'tests'
Requires-Dist: pytest-cov (>=2.0.0) ; extra == 'tests'
